LICENSE
MANIFEST.in
README.md
pyproject.toml
requirements.txt
setup.cfg
setup.py
finetuner/__init__.py
finetuner/callback.py
finetuner/constants.py
finetuner/experiment.py
finetuner/finetuner.py
finetuner/hubble.py
finetuner/models.py
finetuner/names.py
finetuner/run.py
finetuner/client/__init__.py
finetuner/client/base.py
finetuner/client/client.py
finetuner/client/exception.py
finetuner_client.egg-info/PKG-INFO
finetuner_client.egg-info/SOURCES.txt
finetuner_client.egg-info/dependency_links.txt
finetuner_client.egg-info/not-zip-safe
finetuner_client.egg-info/requires.txt
finetuner_client.egg-info/top_level.txt